Apache-License-2.0.txt
LICENSE
MANIFEST.in
OFL-License.txt
README.rst
babel.cfg
setup.cfg
setup.py
bin/preinstall.js
sphinx_rtd_theme_citus/__init__.py
sphinx_rtd_theme_citus/breadcrumbs.html
sphinx_rtd_theme_citus/footer.html
sphinx_rtd_theme_citus/layout.html
sphinx_rtd_theme_citus/search.html
sphinx_rtd_theme_citus/searchbox.html
sphinx_rtd_theme_citus/theme.conf
sphinx_rtd_theme_citus/versions.html
sphinx_rtd_theme_citus.egg-info/PKG-INFO
sphinx_rtd_theme_citus.egg-info/SOURCES.txt
sphinx_rtd_theme_citus.egg-info/dependency_links.txt
sphinx_rtd_theme_citus.egg-info/entry_points.txt
sphinx_rtd_theme_citus.egg-info/not-zip-safe
sphinx_rtd_theme_citus.egg-info/requires.txt
sphinx_rtd_theme_citus.egg-info/top_level.txt
sphinx_rtd_theme_citus/locale/sphinx.pot
sphinx_rtd_theme_citus/locale/de/LC_MESSAGES/sphinx.mo
sphinx_rtd_theme_citus/locale/de/LC_MESSAGES/sphinx.po
sphinx_rtd_theme_citus/locale/en/LC_MESSAGES/sphinx.mo
sphinx_rtd_theme_citus/locale/en/LC_MESSAGES/sphinx.po
sphinx_rtd_theme_citus/locale/es/LC_MESSAGES/sphinx.mo
sphinx_rtd_theme_citus/locale/es/LC_MESSAGES/sphinx.po
sphinx_rtd_theme_citus/locale/et/LC_MESSAGES/sphinx.mo
sphinx_rtd_theme_citus/locale/et/LC_MESSAGES/sphinx.po
sphinx_rtd_theme_citus/locale/fr/LC_MESSAGES/sphinx.mo
sphinx_rtd_theme_citus/locale/fr/LC_MESSAGES/sphinx.po
sphinx_rtd_theme_citus/locale/nl/LC_MESSAGES/sphinx.mo
sphinx_rtd_theme_citus/locale/nl/LC_MESSAGES/sphinx.po
sphinx_rtd_theme_citus/locale/pt_BR/LC_MESSAGES/sphinx.mo
sphinx_rtd_theme_citus/locale/pt_BR/LC_MESSAGES/sphinx.po
sphinx_rtd_theme_citus/locale/ru/LC_MESSAGES/sphinx.mo
sphinx_rtd_theme_citus/locale/ru/LC_MESSAGES/sphinx.po
sphinx_rtd_theme_citus/locale/sv/LC_MESSAGES/sphinx.mo
sphinx_rtd_theme_citus/locale/sv/LC_MESSAGES/sphinx.po
sphinx_rtd_theme_citus/locale/tr/LC_MESSAGES/sphinx.mo
sphinx_rtd_theme_citus/locale/tr/LC_MESSAGES/sphinx.po
sphinx_rtd_theme_citus/locale/zh_CN/LC_MESSAGES/sphinx.mo
sphinx_rtd_theme_citus/locale/zh_CN/LC_MESSAGES/sphinx.po
sphinx_rtd_theme_citus/static/css/badge_only.css
sphinx_rtd_theme_citus/static/css/theme.css
sphinx_rtd_theme_citus/static/css/fonts/Roboto-Slab-Bold.woff
sphinx_rtd_theme_citus/static/css/fonts/Roboto-Slab-Bold.woff2
sphinx_rtd_theme_citus/static/css/fonts/Roboto-Slab-Regular.woff
