Metadata-Version: 2.1
Name: sphinx-rtd-theme-citus
Version: 0.5.19
Summary: Read the Docs theme for Sphinx
Home-page: https://github.com/readthedocs/sphinx_rtd_theme_citus
Author: Dave Snider, Read the Docs, Inc. & contributors
Author-email: dev@readthedocs.org
License: MIT
Project-URL: Homepage, https://sphinx-rtd-theme.readthedocs.io/
Project-URL: Source Code, https://github.com/readthedocs/sphinx_rtd_theme_citus
Project-URL: Issue Tracker, https://github.com/readthedocs/sphinx_rtd_theme_citus/issues
Platform: UNKNOWN
Classifier: Framework :: Sphinx
Classifier: Framework :: Sphinx :: Theme
Classifier: Development Status :: 5 - Production/Stable
Classifier: License :: OSI Approved :: MIT License
Classifier: Environment :: Console
Classifier: Environment :: Web Environment
Classifier: Intended Audience :: Developers
Classifier: Programming Language :: Python :: 2.7
Classifier: Programming Language :: Python :: 3
Classifier: Programming Language :: Python :: 3.6
Classifier: Programming Language :: Python :: 3.7
Classifier: Programming Language :: Python :: 3.8
Classifier: Programming Language :: Python :: 3.9
Classifier: Operating System :: OS Independent
Classifier: Topic :: Documentation
Classifier: Topic :: Software Development :: Documentation
Provides-Extra: dev
License-File: LICENSE
